{
    "os": "Linux-5.10.0-23-amd64-x86_64-with-glibc2.31",
    "python": "3.11.3",
    "heartbeatAt": "2023-06-23T09:34:38.731681",
    "startedAt": "2023-06-23T09:34:38.140131",
    "docker": null,
    "cuda": null,
    "args": [],
    "state": "running",
    "program": "/home/francesco.pugnaloni/TableEmbeddingsWithGNNs/experiments.py",
    "git": {
        "remote": "https://github.com/frapugna/TableEmbeddingsWithGNNs.git",
        "commit": "e52ba35ce7eea46467a5d044571e739b7b2b7dca"
    },
    "email": null,
    "root": "/dati/home/francesco.pugnaloni/TableEmbeddingsWithGNNs",
    "host": "sparc20",
    "username": "francesco.pugnaloni",
    "executable": "/home/francesco.pugnaloni/anaconda3/envs/HPIPyG/bin/python",
    "cpu_count": 12,
    "cpu_count_logical": 24,
    "cpu_freq": {
        "current": 825.1960833333334,
        "min": 0.0,
        "max": 0.0
    },
    "cpu_freq_per_core": [
        {
            "current": 800.127,
            "min": 0.0,
            "max": 0.0
        },
        {
            "current": 800.038,
            "min": 0.0,
            "max": 0.0
        },
        {
            "current": 1066.918,
            "min": 0.0,
            "max": 0.0
        },
        {
            "current": 802.387,
            "min": 0.0,
            "max": 0.0
        },
        {
            "current": 800.554,
            "min": 0.0,
            "max": 0.0
        },
        {
            "current": 800.28,
            "min": 0.0,
            "max": 0.0
        },
        {
            "current": 800.634,
            "min": 0.0,
            "max": 0.0
        },
        {
            "current": 806.546,
            "min": 0.0,
            "max": 0.0
        },
        {
            "current": 800.432,
            "min": 0.0,
            "max": 0.0
        },
        {
            "current": 800.514,
            "min": 0.0,
            "max": 0.0
        },
        {
            "current": 800.9,
            "min": 0.0,
            "max": 0.0
        },
        {
            "current": 799.964,
            "min": 0.0,
            "max": 0.0
        },
        {
            "current": 800.777,
            "min": 0.0,
            "max": 0.0
        },
        {
            "current": 800.039,
            "min": 0.0,
            "max": 0.0
        },
        {
            "current": 984.385,
            "min": 0.0,
            "max": 0.0
        },
        {
            "current": 825.924,
            "min": 0.0,
            "max": 0.0
        },
        {
            "current": 800.071,
            "min": 0.0,
            "max": 0.0
        },
        {
            "current": 871.837,
            "min": 0.0,
            "max": 0.0
        },
        {
            "current": 800.09,
            "min": 0.0,
            "max": 0.0
        },
        {
            "current": 840.861,
            "min": 0.0,
            "max": 0.0
        },
        {
            "current": 800.008,
            "min": 0.0,
            "max": 0.0
        },
        {
            "current": 800.785,
            "min": 0.0,
            "max": 0.0
        },
        {
            "current": 800.169,
            "min": 0.0,
            "max": 0.0
        },
        {
            "current": 800.466,
            "min": 0.0,
            "max": 0.0
        }
    ],
    "disk": {
        "total": 223.40916442871094,
        "used": 15.012100219726562
    },
    "gpu": "Tesla T4",
    "gpu_count": 1,
    "gpu_devices": [
        {
            "name": "Tesla T4",
            "memory_total": 15843721216
        }
    ],
    "memory": {
        "total": 187.19036865234375
    }
}
